{
    "features": [
        {
            "geometry": {
                "coordinates": [
                    [
                        [ -2.6077, 51.47155 ],
                        [ -2.60449, 51.47014 ],
                        [ -2.59837, 51.4667 ],
                        [ -2.59641, 51.46444 ],
                        [ -2.59998, 51.46263 ],
                        [ -2.60869, 51.46203 ],
                        [ -2.60975, 51.46455 ],
                        [ -2.61552, 51.47151 ],
                        [ -2.61036, 51.47249 ],
                        [ -2.6077, 51.47155 ]
                    ]
                ],
                "type": "Polygon"
            },
            "properties": {
                "name": "Bristol 022",
                "rg": "E02003033"
            },
            "type": "Feature"
        },
        {
            "geometry": {
                "coordinates": [
                    [
                        [ -2.56785, 51.46891 ],
                        [ -2.57002, 51.46804 ],
                        [ -2.5738, 51.46683 ],
                        [ -2.57992, 51.4619 ],
                        [ -2.58616, 51.45905 ],
                        [ -2.59106, 51.46076 ],
                        [ -2.59002, 51.46478 ],
                        [ -2.59121, 51.46704 ],
                        [ -2.57471, 51.47365 ],
                        [ -2.56785, 51.46891 ]
                    ]
                ],
                "type": "Polygon"
            },
            "properties": {
                "name": "Bristol 023",
                "rg": "E02003034"
            },
            "type": "Feature"
        },
        {
            "geometry": {
                "coordinates": [
                    [
                        [ -2.59121, 51.46704 ],
                        [ -2.59002, 51.46478 ],
                        [ -2.59106, 51.46076 ],
                        [ -2.58616, 51.45905 ],
                        [ -2.58459, 51.45706 ],
                        [ -2.58854, 51.45801 ],
                        [ -2.59144, 51.45709 ],
                        [ -2.59998, 51.46263 ],
                        [ -2.59641, 51.46444 ],
                        [ -2.59837, 51.4667 ],
                        [ -2.60449, 51.47014 ],
                        [ -2.59788, 51.4691 ],
                        [ -2.59378, 51.47039 ],
                        [ -2.59121, 51.46704 ]
                    ]
                ],
                "type": "Polygon"
            },
            "properties": {
                "name": "Bristol 025",
                "rg": "E02003036"
            },
            "type": "Feature"
        },
        {
            "geometry": {
                "coordinates": [
                    [
                        [ -2.60869, 51.46203 ],
                        [ -2.60872, 51.45583 ],
                        [ -2.61181, 51.4571 ],
                        [ -2.6148, 51.45545 ],
                        [ -2.61821, 51.45766 ],
                        [ -2.6148, 51.45901 ],
                        [ -2.61709, 51.46323 ],
                        [ -2.62023, 51.4661 ],
                        [ -2.62036, 51.46841 ],
                        [ -2.61552, 51.47151 ],
                        [ -2.60975, 51.46455 ],
                        [ -2.60869, 51.46203 ]
                    ]
                ],
                "type": "Polygon"
            },
            "properties": {
                "name": "Bristol 026",
                "rg": "E02003037"
            },
            "type": "Feature"
        },
        {
            "geometry": {
                "coordinates": [
                    [
                        [ -2.51215, 51.46306 ],
                        [ -2.51303, 51.46162 ],
                        [ -2.51846, 51.45908 ],
                        [ -2.51885, 51.45654 ],
                        [ -2.52576, 51.45871 ],
                        [ -2.52621, 51.46183 ],
                        [ -2.52899, 51.46688 ],
                        [ -2.52118, 51.46664 ],
                        [ -2.51287, 51.46718 ],
                        [ -2.51135, 51.46521 ],
                        [ -2.51215, 51.46306 ]
                    ]
                ],
                "type": "Polygon"
            },
            "properties": {
                "name": "Bristol 027",
                "rg": "E02003038"
            },
            "type": "Feature"
        },
        {
            "geometry": {
                "coordinates": [
                    [
                        [ -2.52899, 51.46688 ],
                        [ -2.52621, 51.46183 ],
                        [ -2.52576, 51.45871 ],
                        [ -2.53349, 51.45874 ],
                        [ -2.538, 51.45767 ],
                        [ -2.54267, 51.45774 ],
                        [ -2.54284, 51.46079 ],
                        [ -2.54768, 51.46428 ],
                        [ -2.54156, 51.46582 ],
                        [ -2.52899, 51.46688 ]
                    ]
                ],
                "type": "Polygon"
            },
            "properties": {
                "name": "Bristol 028",
                "rg": "E02003039"
            },
            "type": "Feature"
        },
        {
            "geometry": {
                "coordinates": [
                    [
                        [ -2.55102, 51.46396 ],
                        [ -2.54768, 51.46428 ],
                        [ -2.54284, 51.46079 ],
                        [ -2.54267, 51.45774 ],
                        [ -2.54706, 51.45651 ],
                        [ -2.54683, 51.45462 ],
                        [ -2.55205, 51.452 ],
                        [ -2.55944, 51.45188 ],
                        [ -2.56055, 51.45495 ],
                        [ -2.56305, 51.45766 ],
                        [ -2.55978, 51.4584 ],
                        [ -2.55966, 51.46267 ],
                        [ -2.55634, 51.46336 ],
                        [ -2.55102, 51.46396 ]
                    ]
                ],
                "type": "Polygon"
            },
            "properties": {
                "name": "Bristol 029",
                "rg": "E02003040"
            },
            "type": "Feature"
        },
        {
            "geometry": {
                "coordinates": [
                    [
                        [
                            [ -2.6274, 51.45513 ],
                            [ -2.62984, 51.45761 ],
                            [ -2.62916, 51.46102 ],
                            [ -2.62023, 51.4661 ],
                            [ -2.61709, 51.46323 ],
                            [ -2.6148, 51.45901 ],
                            [ -2.61821, 51.45766 ],
                            [ -2.6148, 51.45545 ],
                            [ -2.61408, 51.45326 ],
                            [ -2.62592, 51.45193 ],
                            [ -2.6274, 51.45513 ]
                        ]
                    ],
                    [
                        [
                            [ -2.62843, 51.45472 ],
                            [ -2.62854, 51.45468 ],
                            [ -2.63181, 51.45762 ],
                            [ -2.63116, 51.45761 ],
                            [ -2.62843, 51.45472 ]
                        ]
                    ]
                ],
                "type": "MultiPolygon"
            },
            "properties": {
                "name": "Bristol 030",
                "rg": "E02003041"
            },
            "type": "Feature"
        },
        {
            "geometry": {
                "coordinates": [
                    [
                        [ -2.59998, 51.46263 ],
                        [ -2.59144, 51.45709 ],
                        [ -2.58854, 51.45801 ],
                        [ -2.58459, 51.45706 ],
                        [ -2.58414, 51.45277 ],
                        [ -2.58928, 51.45484 ],
                        [ -2.59199, 51.45262 ],
                        [ -2.59204, 51.4495 ],
                        [ -2.59037, 51.4485 ],
                        [ -2.59109, 51.44581 ],
                        [ -2.59868, 51.44595 ],
                        [ -2.60828, 51.44675 ],
                        [ -2.6192, 51.44585 ],
                        [ -2.62377, 51.44746 ],
                        [ -2.62408, 51.4495 ],
                        [ -2.62103, 51.44822 ],
                        [ -2.61559, 51.44788 ],
                        [ -2.6083, 51.45064 ],
                        [ -2.61004, 51.45426 ],
                        [ -2.60872, 51.45583 ],
                        [ -2.60869, 51.46203 ],
                        [ -2.59998, 51.46263 ]
                    ]
                ],
                "type": "Polygon"
            },
            "properties": {
                "name": "Bristol 032",
                "rg": "E02003043"
            },
            "type": "Feature"
        },
        {
            "geometry": {
                "coordinates": [
                    [
                        [ -2.52576, 51.45871 ],
                        [ -2.51885, 51.45654 ],
                        [ -2.51894, 51.45261 ],
                        [ -2.52063, 51.45105 ],
                        [ -2.52236, 51.44977 ],
                        [ -2.52993, 51.44823 ],
                        [ -2.53167, 51.44644 ],
                        [ -2.53561, 51.44734 ],
                        [ -2.53433, 51.44939 ],
                        [ -2.53839, 51.45447 ],
                        [ -2.54512, 51.45551 ],
                        [ -2.54683, 51.45462 ],
                        [ -2.54706, 51.45651 ],
                        [ -2.54267, 51.45774 ],
                        [ -2.538, 51.45767 ],
                        [ -2.53349, 51.45874 ],
                        [ -2.52576, 51.45871 ]
                    ]
                ],
                "type": "Polygon"
            },
            "properties": {
                "name": "Bristol 033",
                "rg": "E02003044"
            },
            "type": "Feature"
        },
        {
            "geometry": {
                "coordinates": [
                    [
                        [
                            [ -2.60872, 51.45583 ],
                            [ -2.61004, 51.45426 ],
                            [ -2.6083, 51.45064 ],
                            [ -2.61559, 51.44788 ],
                            [ -2.62103, 51.44822 ],
                            [ -2.62408, 51.4495 ],
                            [ -2.62658, 51.45255 ],
                            [ -2.6274, 51.45513 ],
                            [ -2.62592, 51.45193 ],
                            [ -2.61408, 51.45326 ],
                            [ -2.6148, 51.45545 ],
                            [ -2.61181, 51.4571 ],
                            [ -2.60872, 51.45583 ]
                        ]
                    ],
                    [
                        [
                            [ -2.62622, 51.45038 ],
                            [ -2.62655, 51.45037 ],
                            [ -2.62854, 51.45468 ],
                            [ -2.62843, 51.45472 ],
                            [ -2.62622, 51.45038 ]
                        ]
                    ]
                ],
                "type": "MultiPolygon"
            },
            "properties": {
                "name": "Bristol 034",
                "rg": "E02003045"
            },
            "type": "Feature"
        },
        {
            "geometry": {
                "coordinates": [
                    [
                        [ -2.53561, 51.44734 ],
                        [ -2.53861, 51.4466 ],
                        [ -2.54285, 51.44634 ],
                        [ -2.54665, 51.44743 ],
                        [ -2.54868, 51.44283 ],
                        [ -2.55085, 51.44215 ],
                        [ -2.55193, 51.4377 ],
                        [ -2.55616, 51.43849 ],
                        [ -2.55881, 51.44425 ],
                        [ -2.56156, 51.442 ],
                        [ -2.56445, 51.44236 ],
                        [ -2.56733, 51.44279 ],
                        [ -2.57338, 51.44251 ],
                        [ -2.57323, 51.44311 ],
                        [ -2.57085, 51.44284 ],
                        [ -2.5667, 51.44417 ],
                        [ -2.56108, 51.44485 ],
                        [ -2.55784, 51.44638 ],
                        [ -2.55858, 51.44881 ],
                        [ -2.55395, 51.45106 ],
                        [ -2.55205, 51.452 ],
                        [ -2.54683, 51.45462 ],
                        [ -2.54512, 51.45551 ],
                        [ -2.53839, 51.45447 ],
                        [ -2.53433, 51.44939 ],
                        [ -2.53561, 51.44734 ]
                    ]
                ],
                "type": "Polygon"
            },
            "properties": {
                "name": "Bristol 035",
                "rg": "E02003046"
            },
            "type": "Feature"
        },
        {
            "geometry": {
                "coordinates": [
                    [
                        [ -2.59881, 51.44562 ],
                        [ -2.6021, 51.44137 ],
                        [ -2.60705, 51.4403 ],
                        [ -2.61052, 51.44044 ],
                        [ -2.62048, 51.43664 ],
                        [ -2.62442, 51.44073 ],
                        [ -2.63029, 51.43948 ],
                        [ -2.63423, 51.43928 ],
                        [ -2.64008, 51.44045 ],
                        [ -2.63512, 51.44565 ],
                        [ -2.63309, 51.44724 ],
                        [ -2.627, 51.44667 ],
                        [ -2.62655, 51.45037 ],
                        [ -2.62622, 51.45038 ],
                        [ -2.62496, 51.4473 ],
                        [ -2.62159, 51.44561 ],
                        [ -2.6183, 51.44535 ],
                        [ -2.60683, 51.44643 ],
                        [ -2.59881, 51.44562 ]
                    ]
                ],
                "type": "Polygon"
            },
            "properties": {
                "name": "Bristol 036",
                "rg": "E02003047"
            },
            "type": "Feature"
        },
        {
            "geometry": {
                "coordinates": [
                    [
                        [ -2.57323, 51.44311 ],
                        [ -2.57338, 51.44251 ],
                        [ -2.56733, 51.44279 ],
                        [ -2.57009, 51.4397 ],
                        [ -2.57702, 51.43745 ],
                        [ -2.58195, 51.43641 ],
                        [ -2.58981, 51.43965 ],
                        [ -2.58665, 51.44056 ],
                        [ -2.58741, 51.44292 ],
                        [ -2.58103, 51.44501 ],
                        [ -2.5801, 51.448 ],
                        [ -2.57734, 51.44694 ],
                        [ -2.57782, 51.44473 ],
                        [ -2.57635, 51.44364 ],
                        [ -2.57323, 51.44311 ]
                    ]
                ],
                "type": "Polygon"
            },
            "properties": {
                "name": "Bristol 037",
                "rg": "E02003048"
            },
            "type": "Feature"
        },
        {
            "geometry": {
                "coordinates": [
                    [
                        [ -2.53861, 51.4466 ],
                        [ -2.53663, 51.44459 ],
                        [ -2.53212, 51.44548 ],
                        [ -2.52832, 51.44495 ],
                        [ -2.52652, 51.44347 ],
                        [ -2.52702, 51.43618 ],
                        [ -2.5218, 51.43176 ],
                        [ -2.51344, 51.42963 ],
                        [ -2.51046, 51.42878 ],
                        [ -2.52126, 51.43123 ],
                        [ -2.52546, 51.43294 ],
                        [ -2.52739, 51.4315 ],
                        [ -2.52369, 51.42984 ],
                        [ -2.52321, 51.42614 ],
                        [ -2.52767, 51.42683 ],
                        [ -2.54436, 51.43081 ],
                        [ -2.5485, 51.43403 ],
                        [ -2.5522, 51.43403 ],
                        [ -2.55193, 51.4377 ],
                        [ -2.55085, 51.44215 ],
                        [ -2.54868, 51.44283 ],
                        [ -2.54665, 51.44743 ],
                        [ -2.54285, 51.44634 ],
                        [ -2.53861, 51.4466 ]
                    ]
                ],
                "type": "Polygon"
            },
            "properties": {
                "name": "Bristol 038",
                "rg": "E02003049"
            },
            "type": "Feature"
        },
        {
            "geometry": {
                "coordinates": [
                    [
                        [ -2.58741, 51.44292 ],
                        [ -2.59414, 51.44042 ],
                        [ -2.59978, 51.43741 ],
                        [ -2.59786, 51.43567 ],
                        [ -2.60071, 51.43041 ],
                        [ -2.60451, 51.4293 ],
                        [ -2.61178, 51.43193 ],
                        [ -2.61635, 51.43051 ],
                        [ -2.61406, 51.43341 ],
                        [ -2.60901, 51.43385 ],
                        [ -2.6093, 51.43572 ],
                        [ -2.60567, 51.43774 ],
                        [ -2.60705, 51.4403 ],
                        [ -2.6021, 51.44137 ],
                        [ -2.59881, 51.44562 ],
                        [ -2.59399, 51.44581 ],
                        [ -2.58895, 51.44506 ],
                        [ -2.5848, 51.44572 ],
                        [ -2.5801, 51.448 ],
                        [ -2.58103, 51.44501 ],
                        [ -2.58741, 51.44292 ]
                    ]
                ],
                "type": "Polygon"
            },
            "properties": {
                "name": "Bristol 039",
                "rg": "E02003050"
            },
            "type": "Feature"
        },
        {
            "geometry": {
                "coordinates": [
                    [
                        [ -2.58195, 51.43641 ],
                        [ -2.59022, 51.43216 ],
                        [ -2.59443, 51.4311 ],
                        [ -2.59734, 51.42845 ],
                        [ -2.60071, 51.43041 ],
                        [ -2.59786, 51.43567 ],
                        [ -2.59978, 51.43741 ],
                        [ -2.59414, 51.44042 ],
                        [ -2.58741, 51.44292 ],
                        [ -2.58665, 51.44056 ],
                        [ -2.58981, 51.43965 ],
                        [ -2.58195, 51.43641 ]
                    ]
                ],
                "type": "Polygon"
            },
            "properties": {
                "name": "Bristol 040",
                "rg": "E02003051"
            },
            "type": "Feature"
        },
        {
            "geometry": {
                "coordinates": [
                    [
                        [ -2.60705, 51.4403 ],
                        [ -2.60567, 51.43774 ],
                        [ -2.6093, 51.43572 ],
                        [ -2.60901, 51.43385 ],
                        [ -2.61406, 51.43341 ],
                        [ -2.61635, 51.43051 ],
                        [ -2.62258, 51.42881 ],
                        [ -2.63393, 51.42751 ],
                        [ -2.6335, 51.43581 ],
                        [ -2.62952, 51.43737 ],
                        [ -2.63029, 51.43948 ],
                        [ -2.62442, 51.44073 ],
                        [ -2.62048, 51.43664 ],
                        [ -2.61052, 51.44044 ],
                        [ -2.60705, 51.4403 ]
                    ]
                ],
                "type": "Polygon"
            },
            "properties": {
                "name": "Bristol 041",
                "rg": "E02003052"
            },
            "type": "Feature"
        },
        {
            "geometry": {
                "coordinates": [
                    [
                        [ -2.56445, 51.44236 ],
                        [ -2.56329, 51.43708 ],
                        [ -2.56018, 51.43428 ],
                        [ -2.56173, 51.43053 ],
                        [ -2.55833, 51.42946 ],
                        [ -2.56385, 51.42722 ],
                        [ -2.57004, 51.42636 ],
                        [ -2.57322, 51.42752 ],
                        [ -2.57538, 51.42983 ],
                        [ -2.57431, 51.43345 ],
                        [ -2.57694, 51.43523 ],
                        [ -2.57702, 51.43745 ],
                        [ -2.57009, 51.4397 ],
                        [ -2.56733, 51.44279 ],
                        [ -2.56445, 51.44236 ]
                    ]
                ],
                "type": "Polygon"
            },
            "properties": {
                "name": "Bristol 042",
                "rg": "E02003053"
            },
            "type": "Feature"
        },
        {
            "geometry": {
                "coordinates": [
                    [
                        [ -2.55193, 51.4377 ],
                        [ -2.5522, 51.43403 ],
                        [ -2.5485, 51.43403 ],
                        [ -2.54436, 51.43081 ],
                        [ -2.52767, 51.42683 ],
                        [ -2.52321, 51.42614 ],
                        [ -2.52673, 51.42576 ],
                        [ -2.53131, 51.42331 ],
                        [ -2.52946, 51.42092 ],
                        [ -2.53376, 51.41821 ],
                        [ -2.53577, 51.41839 ],
                        [ -2.53978, 51.42194 ],
                        [ -2.54451, 51.42312 ],
                        [ -2.54594, 51.42651 ],
                        [ -2.54792, 51.42754 ],
                        [ -2.55187, 51.42534 ],
                        [ -2.5561, 51.42725 ],
                        [ -2.55833, 51.42946 ],
                        [ -2.56173, 51.43053 ],
                        [ -2.56018, 51.43428 ],
                        [ -2.56329, 51.43708 ],
                        [ -2.56445, 51.44236 ],
                        [ -2.56156, 51.442 ],
                        [ -2.55881, 51.44425 ],
                        [ -2.55616, 51.43849 ],
                        [ -2.55193, 51.4377 ]
                    ]
                ],
                "type": "Polygon"
            },
            "properties": {
                "name": "Bristol 043",
                "rg": "E02003054"
            },
            "type": "Feature"
        },
        {
            "geometry": {
                "coordinates": [
                    [
                        [ -2.57004, 51.42636 ],
                        [ -2.57667, 51.4227 ],
                        [ -2.58524, 51.41951 ],
                        [ -2.58515, 51.42633 ],
                        [ -2.58753, 51.43011 ],
                        [ -2.59022, 51.43216 ],
                        [ -2.58195, 51.43641 ],
                        [ -2.57702, 51.43745 ],
                        [ -2.57694, 51.43523 ],
                        [ -2.57431, 51.43345 ],
                        [ -2.57538, 51.42983 ],
                        [ -2.57322, 51.42752 ],
                        [ -2.57004, 51.42636 ]
                    ]
                ],
                "type": "Polygon"
            },
            "properties": {
                "name": "Bristol 044",
                "rg": "E02003055"
            },
            "type": "Feature"
        },
        {
            "geometry": {
                "coordinates": [
                    [
                        [ -2.58524, 51.41951 ],
                        [ -2.59356, 51.41488 ],
                        [ -2.59361, 51.41416 ],
                        [ -2.59433, 51.41384 ],
                        [ -2.59537, 51.41475 ],
                        [ -2.59634, 51.4165 ],
                        [ -2.60186, 51.41971 ],
                        [ -2.60434, 51.42241 ],
                        [ -2.60435, 51.42612 ],
                        [ -2.60451, 51.4293 ],
                        [ -2.60071, 51.43041 ],
                        [ -2.59734, 51.42845 ],
                        [ -2.59443, 51.4311 ],
                        [ -2.59022, 51.43216 ],
                        [ -2.58753, 51.43011 ],
                        [ -2.58515, 51.42633 ],
                        [ -2.58524, 51.41951 ]
                    ]
                ],
                "type": "Polygon"
            },
            "properties": {
                "name": "Bristol 045",
                "rg": "E02003056"
            },
            "type": "Feature"
        },
        {
            "geometry": {
                "coordinates": [
                    [
                        [ -2.60451, 51.4293 ],
                        [ -2.60435, 51.42612 ],
                        [ -2.61058, 51.42214 ],
                        [ -2.61426, 51.42118 ],
                        [ -2.6174, 51.41851 ],
                        [ -2.61937, 51.41403 ],
                        [ -2.62457, 51.41876 ],
                        [ -2.62751, 51.41848 ],
                        [ -2.62907, 51.41604 ],
                        [ -2.63246, 51.42035 ],
                        [ -2.63709, 51.4232 ],
                        [ -2.63393, 51.42751 ],
                        [ -2.62258, 51.42881 ],
                        [ -2.61635, 51.43051 ],
                        [ -2.61178, 51.43193 ],
                        [ -2.60451, 51.4293 ]
                    ]
                ],
                "type": "Polygon"
            },
            "properties": {
                "name": "Bristol 046",
                "rg": "E02003057"
            },
            "type": "Feature"
        },
        {
            "geometry": {
                "coordinates": [
                    [
                        [ -2.56385, 51.42722 ],
                        [ -2.56063, 51.41902 ],
                        [ -2.55881, 51.41123 ],
                        [ -2.56137, 51.41065 ],
                        [ -2.56696, 51.41228 ],
                        [ -2.57397, 51.41317 ],
                        [ -2.5764, 51.41116 ],
                        [ -2.58497, 51.41205 ],
                        [ -2.58757, 51.41106 ],
                        [ -2.59361, 51.41416 ],
                        [ -2.59356, 51.41488 ],
                        [ -2.58524, 51.41951 ],
                        [ -2.57667, 51.4227 ],
                        [ -2.57004, 51.42636 ],
                        [ -2.56385, 51.42722 ]
                    ]
                ],
                "type": "Polygon"
            },
            "properties": {
                "name": "Bristol 047",
                "rg": "E02003058"
            },
            "type": "Feature"
        },
        {
            "geometry": {
                "coordinates": [
                    [
                        [ -2.59537, 51.41475 ],
                        [ -2.60272, 51.41352 ],
                        [ -2.60424, 51.41157 ],
                        [ -2.60819, 51.40995 ],
                        [ -2.62026, 51.41019 ],
                        [ -2.61937, 51.41403 ],
                        [ -2.6174, 51.41851 ],
                        [ -2.61426, 51.42118 ],
                        [ -2.61058, 51.42214 ],
                        [ -2.60435, 51.42612 ],
                        [ -2.60434, 51.42241 ],
                        [ -2.60186, 51.41971 ],
                        [ -2.59634, 51.4165 ],
                        [ -2.59537, 51.41475 ]
                    ]
                ],
                "type": "Polygon"
            },
            "properties": {
                "name": "Bristol 048",
                "rg": "E02003059"
            },
            "type": "Feature"
        },
        {
            "geometry": {
                "coordinates": [
                    [
                        [ -2.53376, 51.41821 ],
                        [ -2.5345, 51.41385 ],
                        [ -2.54235, 51.40871 ],
                        [ -2.55587, 51.40928 ],
                        [ -2.55881, 51.41123 ],
                        [ -2.56063, 51.41902 ],
                        [ -2.56385, 51.42722 ],
                        [ -2.55833, 51.42946 ],
                        [ -2.5561, 51.42725 ],
                        [ -2.55187, 51.42534 ],
                        [ -2.54792, 51.42754 ],
                        [ -2.54594, 51.42651 ],
                        [ -2.54451, 51.42312 ],
                        [ -2.53978, 51.42194 ],
                        [ -2.53577, 51.41839 ],
                        [ -2.53376, 51.41821 ]
                    ]
                ],
                "type": "Polygon"
            },
            "properties": {
                "name": "Bristol 049",
                "rg": "E02003060"
            },
            "type": "Feature"
        },
        {
            "geometry": {
                "coordinates": [
                    [
                        [ -2.61937, 51.41403 ],
                        [ -2.62026, 51.41019 ],
                        [ -2.623, 51.40386 ],
                        [ -2.62796, 51.40186 ],
                        [ -2.63329, 51.40348 ],
                        [ -2.63547, 51.40698 ],
                        [ -2.63197, 51.40818 ],
                        [ -2.62907, 51.41604 ],
                        [ -2.62751, 51.41848 ],
                        [ -2.62457, 51.41876 ],
                        [ -2.61937, 51.41403 ]
                    ]
                ],
                "type": "Polygon"
            },
            "properties": {
                "name": "Bristol 050",
                "rg": "E02003061"
            },
            "type": "Feature"
        },
        {
            "geometry": {
                "coordinates": [
                    [
                        [ -2.59433, 51.41384 ],
                        [ -2.59468, 51.41066 ],
                        [ -2.60256, 51.40986 ],
                        [ -2.60298, 51.40766 ],
                        [ -2.60553, 51.40514 ],
                        [ -2.60964, 51.40378 ],
                        [ -2.6104, 51.40127 ],
                        [ -2.61234, 51.40227 ],
                        [ -2.61747, 51.4024 ],
                        [ -2.61966, 51.40438 ],
                        [ -2.623, 51.40386 ],
                        [ -2.62026, 51.41019 ],
                        [ -2.60819, 51.40995 ],
                        [ -2.60424, 51.41157 ],
                        [ -2.60272, 51.41352 ],
                        [ -2.59537, 51.41475 ],
                        [ -2.59433, 51.41384 ]
                    ]
                ],
                "type": "Polygon"
            },
            "properties": {
                "name": "Bristol 051",
                "rg": "E02003062"
            },
            "type": "Feature"
        },
        {
            "geometry": {
                "coordinates": [
                    [
                        [ -2.56137, 51.41065 ],
                        [ -2.56318, 51.40747 ],
                        [ -2.56685, 51.40474 ],
                        [ -2.5665, 51.40278 ],
                        [ -2.57075, 51.39937 ],
                        [ -2.57635, 51.40112 ],
                        [ -2.5781, 51.39936 ],
                        [ -2.58201, 51.40089 ],
                        [ -2.5844, 51.40041 ],
                        [ -2.58153, 51.40879 ],
                        [ -2.58757, 51.41106 ],
                        [ -2.58497, 51.41205 ],
                        [ -2.5764, 51.41116 ],
                        [ -2.57397, 51.41317 ],
                        [ -2.56696, 51.41228 ],
                        [ -2.56137, 51.41065 ]
                    ]
                ],
                "type": "Polygon"
            },
            "properties": {
                "name": "Bristol 052",
                "rg": "E02003063"
            },
            "type": "Feature"
        },
        {
            "geometry": {
                "coordinates": [
                    [
                        [ -2.61583, 51.50233 ],
                        [ -2.61625, 51.50422 ],
                        [ -2.62332, 51.5025 ],
                        [ -2.62413, 51.50048 ],
                        [ -2.62776, 51.50116 ],
                        [ -2.63768, 51.50012 ],
                        [ -2.63958, 51.50184 ],
                        [ -2.64184, 51.50674 ],
                        [ -2.64706, 51.50933 ],
                        [ -2.64721, 51.51217 ],
                        [ -2.63878, 51.51205 ],
                        [ -2.62786, 51.51451 ],
                        [ -2.62109, 51.51487 ],
                        [ -2.60929, 51.51339 ],
                        [ -2.60244, 51.51378 ],
                        [ -2.59576, 51.51535 ],
                        [ -2.59905, 51.51207 ],
                        [ -2.60963, 51.50607 ],
                        [ -2.61166, 51.50365 ],
                        [ -2.61583, 51.50233 ]
                    ]
                ],
                "type": "Polygon"
            },
            "properties": {
                "name": "Bristol 001",
                "rg": "E02003012"
            },
            "type": "Feature"
        },
        {
            "geometry": {
                "coordinates": [
                    [
                        [ -2.58099, 51.51741 ],
                        [ -2.58329, 51.51288 ],
                        [ -2.58927, 51.51151 ],
                        [ -2.59122, 51.50968 ],
                        [ -2.58839, 51.50735 ],
                        [ -2.58773, 51.50353 ],
                        [ -2.59206, 51.50127 ],
                        [ -2.59999, 51.49563 ],
                        [ -2.60238, 51.49744 ],
                        [ -2.60706, 51.49688 ],
                        [ -2.60913, 51.4982 ],
                        [ -2.6151, 51.49594 ],
                        [ -2.61649, 51.4993 ],
                        [ -2.61583, 51.50233 ],
                        [ -2.61166, 51.50365 ],
                        [ -2.60963, 51.50607 ],
                        [ -2.59905, 51.51207 ],
                        [ -2.59576, 51.51535 ],
                        [ -2.58799, 51.51706 ],
                        [ -2.58099, 51.51741 ]
                    ]
                ],
                "type": "Polygon"
            },
            "properties": {
                "name": "Bristol 002",
                "rg": "E02003013"
            },
            "type": "Feature"
        },
        {
            "geometry": {
                "coordinates": [
                    [
                        [ -2.64721, 51.51217 ],
                        [ -2.64706, 51.50933 ],
                        [ -2.64184, 51.50674 ],
                        [ -2.63958, 51.50184 ],
                        [ -2.64602, 51.50021 ],
                        [ -2.64905, 51.49869 ],
                        [ -2.65744, 51.50048 ],
                        [ -2.66063, 51.49497 ],
                        [ -2.66463, 51.49238 ],
                        [ -2.66331, 51.49118 ],
                        [ -2.67249, 51.48894 ],
                        [ -2.67387, 51.49177 ],
                        [ -2.68182, 51.49393 ],
                        [ -2.68473, 51.4961 ],
                        [ -2.68239, 51.50057 ],
                        [ -2.68361, 51.50244 ],
                        [ -2.68694, 51.50262 ],
                        [ -2.68803, 51.50499 ],
                        [ -2.69448, 51.50627 ],
                        [ -2.68516, 51.5086 ],
                        [ -2.68334, 51.51195 ],
                        [ -2.68584, 51.51946 ],
                        [ -2.68916, 51.52163 ],
                        [ -2.68652, 51.52275 ],
                        [ -2.68356, 51.52698 ],
                        [ -2.67947, 51.52741 ],
                        [ -2.67593, 51.53133 ],
                        [ -2.67923, 51.53254 ],
                        [ -2.6826, 51.53518 ],
                        [ -2.67381, 51.54443 ],
                        [ -2.66369, 51.537 ],
                        [ -2.66566, 51.53379 ],
                        [ -2.66542, 51.53097 ],
                        [ -2.65741, 51.52594 ],
                        [ -2.6514, 51.5207 ],
                        [ -2.65383, 51.51819 ],
                        [ -2.65449, 51.51372 ],
                        [ -2.64721, 51.51217 ]
                    ]
                ],
                "type": "Polygon"
            },
            "properties": {
                "name": "Bristol 003",
                "rg": "E02003014"
            },
            "type": "Feature"
        },
        {
            "geometry": {
                "coordinates": [
                    [
                        [ -2.58047, 51.50098 ],
                        [ -2.5791, 51.4981 ],
                        [ -2.58231, 51.49422 ],
                        [ -2.58357, 51.4924 ],
                        [ -2.58772, 51.49086 ],
                        [ -2.58479, 51.48887 ],
                        [ -2.59058, 51.48795 ],
                        [ -2.59797, 51.49215 ],
                        [ -2.60362, 51.49274 ],
                        [ -2.59999, 51.49563 ],
                        [ -2.59206, 51.50127 ],
                        [ -2.58773, 51.50353 ],
                        [ -2.58047, 51.50098 ]
                    ]
                ],
                "type": "Polygon"
            },
            "properties": {
                "name": "Bristol 004",
                "rg": "E02003015"
            },
            "type": "Feature"
        },
        {
            "geometry": {
                "coordinates": [
                    [
                        [ -2.56735, 51.49875 ],
                        [ -2.56479, 51.49552 ],
                        [ -2.56719, 51.49251 ],
                        [ -2.56649, 51.49092 ],
                        [ -2.56938, 51.48854 ],
                        [ -2.57258, 51.48949 ],
                        [ -2.57786, 51.49014 ],
                        [ -2.57881, 51.49341 ],
                        [ -2.58231, 51.49422 ],
                        [ -2.5791, 51.4981 ],
                        [ -2.58047, 51.50098 ],
                        [ -2.5731, 51.5004 ],
                        [ -2.56735, 51.49875 ]
                    ]
                ],
                "type": "Polygon"
            },
            "properties": {
                "name": "Bristol 005",
                "rg": "E02003016"
            },
            "type": "Feature"
        },
        {
            "geometry": {
                "coordinates": [
                    [
                        [ -2.59999, 51.49563 ],
                        [ -2.60362, 51.49274 ],
                        [ -2.6122, 51.49237 ],
                        [ -2.61073, 51.48994 ],
                        [ -2.60745, 51.48932 ],
                        [ -2.60919, 51.48647 ],
                        [ -2.6128, 51.48381 ],
                        [ -2.61627, 51.48444 ],
                        [ -2.61706, 51.4875 ],
                        [ -2.62034, 51.48892 ],
                        [ -2.62177, 51.49183 ],
                        [ -2.62208, 51.49615 ],
                        [ -2.61649, 51.4993 ],
                        [ -2.6151, 51.49594 ],
                        [ -2.60913, 51.4982 ],
                        [ -2.60706, 51.49688 ],
                        [ -2.60238, 51.49744 ],
                        [ -2.59999, 51.49563 ]
                    ]
                ],
                "type": "Polygon"
            },
            "properties": {
                "name": "Bristol 006",
                "rg": "E02003017"
            },
            "type": "Feature"
        },
        {
            "geometry": {
                "coordinates": [
                    [
                        [
                            [ -2.63803, 51.49236 ],
                            [ -2.64197, 51.49173 ],
                            [ -2.64348, 51.48931 ],
                            [ -2.6433, 51.48582 ],
                            [ -2.64835, 51.48087 ],
                            [ -2.65125, 51.48051 ],
                            [ -2.65966, 51.48712 ],
                            [ -2.66288, 51.48792 ],
                            [ -2.66331, 51.49118 ],
                            [ -2.66463, 51.49238 ],
                            [ -2.66063, 51.49497 ],
                            [ -2.65744, 51.50048 ],
                            [ -2.64905, 51.49869 ],
                            [ -2.64602, 51.50021 ],
                            [ -2.63958, 51.50184 ],
                            [ -2.63768, 51.50012 ],
                            [ -2.63931, 51.4971 ],
                            [ -2.63683, 51.4953 ],
                            [ -2.63803, 51.49236 ]
                        ]
                    ],
                    [
                        [
                            [ -2.65227, 51.47936 ],
                            [ -2.65262, 51.47921 ],
                            [ -2.66105, 51.48611 ],
                            [ -2.66285, 51.48672 ],
                            [ -2.66285, 51.48702 ],
                            [ -2.66053, 51.48617 ],
                            [ -2.65227, 51.47936 ]
                        ]
                    ]
                ],
                "type": "MultiPolygon"
            },
            "properties": {
                "name": "Bristol 007",
                "rg": "E02003018"
            },
            "type": "Feature"
        },
        {
            "geometry": {
                "coordinates": [
                    [
                        [
                            [ -2.6826, 51.53518 ],
                            [ -2.67923, 51.53254 ],
                            [ -2.67593, 51.53133 ],
                            [ -2.67947, 51.52741 ],
                            [ -2.68356, 51.52698 ],
                            [ -2.68652, 51.52275 ],
                            [ -2.68916, 51.52163 ],
                            [ -2.68584, 51.51946 ],
                            [ -2.68334, 51.51195 ],
                            [ -2.68516, 51.5086 ],
                            [ -2.69448, 51.50627 ],
                            [ -2.68803, 51.50499 ],
                            [ -2.68694, 51.50262 ],
                            [ -2.68361, 51.50244 ],
                            [ -2.68239, 51.50057 ],
                            [ -2.68473, 51.4961 ],
                            [ -2.68182, 51.49393 ],
                            [ -2.67387, 51.49177 ],
                            [ -2.67249, 51.48894 ],
                            [ -2.66331, 51.49118 ],
                            [ -2.66288, 51.48792 ],
                            [ -2.66626, 51.48684 ],
                            [ -2.66805, 51.48388 ],
                            [ -2.67519, 51.48076 ],
                            [ -2.67875, 51.4809 ],
                            [ -2.68578, 51.48458 ],
                            [ -2.69721, 51.49332 ],
                            [ -2.70944, 51.49842 ],
                            [ -2.71009, 51.50222 ],
                            [ -2.71617, 51.50699 ],
                            [ -2.71095, 51.5111 ],
                            [ -2.70295, 51.51535 ],
                            [ -2.69274, 51.52468 ],
                            [ -2.6826, 51.53518 ]
                        ]
                    ],
                    [
                        [
                            [ -2.66285, 51.48702 ],
                            [ -2.66285, 51.48672 ],
                            [ -2.66548, 51.48403 ],
                            [ -2.67051, 51.48118 ],
                            [ -2.67453, 51.47985 ],
                            [ -2.67591, 51.47968 ],
                            [ -2.67982, 51.48021 ],
                            [ -2.68393, 51.48168 ],
                            [ -2.68756, 51.48377 ],
                            [ -2.69463, 51.48901 ],
                            [ -2.70173, 51.49361 ],
                            [ -2.70332, 51.4942 ],
                            [ -2.70503, 51.49426 ],
                            [ -2.70595, 51.49481 ],
                            [ -2.70828, 51.49532 ],
                            [ -2.70988, 51.49581 ],
                            [ -2.71253, 51.49745 ],
                            [ -2.70887, 51.49554 ],
                            [ -2.70319, 51.49424 ],
                            [ -2.70157, 51.49362 ],
                            [ -2.69335, 51.48831 ],
                            [ -2.68876, 51.48474 ],
                            [ -2.68171, 51.4809 ],
                            [ -2.67962, 51.48021 ],
                            [ -2.67474, 51.47986 ],
                            [ -2.67048, 51.48125 ],
                            [ -2.66589, 51.48387 ],
                            [ -2.66285, 51.48702 ]
                        ]
                    ]
                ],
                "type": "MultiPolygon"
            },
            "properties": {
                "name": "Bristol 008",
                "rg": "E02003019"
            },
            "type": "Feature"
        },
        {
            "geometry": {
                "coordinates": [
                    [
                        [ -2.61583, 51.50233 ],
                        [ -2.61649, 51.4993 ],
                        [ -2.62208, 51.49615 ],
                        [ -2.62177, 51.49183 ],
                        [ -2.62034, 51.48892 ],
                        [ -2.61706, 51.4875 ],
                        [ -2.61627, 51.48444 ],
                        [ -2.61713, 51.47951 ],
                        [ -2.62001, 51.47943 ],
                        [ -2.62897, 51.48391 ],
                        [ -2.63206, 51.48746 ],
                        [ -2.63803, 51.49236 ],
                        [ -2.63683, 51.4953 ],
                        [ -2.63931, 51.4971 ],
                        [ -2.63768, 51.50012 ],
                        [ -2.62776, 51.50116 ],
                        [ -2.62413, 51.50048 ],
                        [ -2.62332, 51.5025 ],
                        [ -2.61625, 51.50422 ],
                        [ -2.61583, 51.50233 ]
                    ]
                ],
                "type": "Polygon"
            },
            "properties": {
                "name": "Bristol 009",
                "rg": "E02003020"
            },
            "type": "Feature"
        },
        {
            "geometry": {
                "coordinates": [
                    [
                        [ -2.57258, 51.48949 ],
                        [ -2.57113, 51.48421 ],
                        [ -2.57334, 51.48283 ],
                        [ -2.57816, 51.48379 ],
                        [ -2.5765, 51.48055 ],
                        [ -2.58219, 51.48131 ],
                        [ -2.58322, 51.48419 ],
                        [ -2.58995, 51.48497 ],
                        [ -2.59152, 51.4873 ],
                        [ -2.59058, 51.48795 ],
                        [ -2.58479, 51.48887 ],
                        [ -2.58772, 51.49086 ],
                        [ -2.58357, 51.4924 ],
                        [ -2.58231, 51.49422 ],
                        [ -2.57881, 51.49341 ],
                        [ -2.57786, 51.49014 ],
                        [ -2.57258, 51.48949 ]
                    ]
                ],
                "type": "Polygon"
            },
            "properties": {
                "name": "Bristol 010",
                "rg": "E02003021"
            },
            "type": "Feature"
        },
        {
            "geometry": {
                "coordinates": [
                    [
                        [ -2.59058, 51.48795 ],
                        [ -2.59152, 51.4873 ],
                        [ -2.60092, 51.48262 ],
                        [ -2.60676, 51.47922 ],
                        [ -2.61151, 51.48162 ],
                        [ -2.6128, 51.48381 ],
                        [ -2.60919, 51.48647 ],
                        [ -2.60745, 51.48932 ],
                        [ -2.61073, 51.48994 ],
                        [ -2.6122, 51.49237 ],
                        [ -2.60362, 51.49274 ],
                        [ -2.59797, 51.49215 ],
                        [ -2.59058, 51.48795 ]
                    ]
                ],
                "type": "Polygon"
            },
            "properties": {
                "name": "Bristol 011",
                "rg": "E02003022"
            },
            "type": "Feature"
        },
        {
            "geometry": {
                "coordinates": [
                    [
                        [ -2.51586, 51.49387 ],
                        [ -2.51501, 51.4921 ],
                        [ -2.51692, 51.49067 ],
                        [ -2.52489, 51.48953 ],
                        [ -2.52872, 51.48601 ],
                        [ -2.53165, 51.4875 ],
                        [ -2.53868, 51.48716 ],
                        [ -2.54221, 51.48292 ],
                        [ -2.53669, 51.4816 ],
                        [ -2.53428, 51.47917 ],
                        [ -2.53898, 51.48035 ],
                        [ -2.54084, 51.47735 ],
                        [ -2.54605, 51.47745 ],
                        [ -2.54751, 51.47856 ],
                        [ -2.54463, 51.48114 ],
                        [ -2.55566, 51.48133 ],
                        [ -2.55922, 51.48049 ],
                        [ -2.56035, 51.47864 ],
                        [ -2.56025, 51.48162 ],
                        [ -2.55616, 51.48585 ],
                        [ -2.54054, 51.49306 ],
                        [ -2.53433, 51.49674 ],
                        [ -2.53028, 51.49641 ],
                        [ -2.52775, 51.49492 ],
                        [ -2.52747, 51.49265 ],
                        [ -2.51823, 51.49297 ],
                        [ -2.51586, 51.49387 ]
                    ]
                ],
                "type": "Polygon"
            },
            "properties": {
                "name": "Bristol 012",
                "rg": "E02003023"
            },
            "type": "Feature"
        },
        {
            "geometry": {
                "coordinates": [
                    [
                        [ -2.51513, 51.48176 ],
                        [ -2.51523, 51.48145 ],
                        [ -2.52154, 51.48169 ],
                        [ -2.52295, 51.47862 ],
                        [ -2.5258, 51.47834 ],
                        [ -2.53604, 51.47675 ],
                        [ -2.53428, 51.47917 ],
                        [ -2.53669, 51.4816 ],
                        [ -2.54221, 51.48292 ],
                        [ -2.53868, 51.48716 ],
                        [ -2.53165, 51.4875 ],
                        [ -2.52872, 51.48601 ],
                        [ -2.52489, 51.48953 ],
                        [ -2.51692, 51.49067 ],
                        [ -2.51501, 51.4921 ],
                        [ -2.511, 51.48999 ],
                        [ -2.51671, 51.48516 ],
                        [ -2.51513, 51.48176 ]
                    ]
                ],
                "type": "Polygon"
            },
            "properties": {
                "name": "Bristol 013",
                "rg": "E02003024"
            },
            "type": "Feature"
        },
        {
            "geometry": {
                "coordinates": [
                    [
                        [ -2.53433, 51.49674 ],
                        [ -2.54054, 51.49306 ],
                        [ -2.55616, 51.48585 ],
                        [ -2.56025, 51.48162 ],
                        [ -2.56035, 51.47864 ],
                        [ -2.56077, 51.47475 ],
                        [ -2.56194, 51.47296 ],
                        [ -2.56785, 51.46891 ],
                        [ -2.57471, 51.47365 ],
                        [ -2.57611, 51.47564 ],
                        [ -2.5765, 51.48055 ],
                        [ -2.57816, 51.48379 ],
                        [ -2.57334, 51.48283 ],
                        [ -2.57113, 51.48421 ],
                        [ -2.57258, 51.48949 ],
                        [ -2.56938, 51.48854 ],
                        [ -2.56649, 51.49092 ],
                        [ -2.56719, 51.49251 ],
                        [ -2.56479, 51.49552 ],
                        [ -2.56008, 51.49644 ],
                        [ -2.55466, 51.49635 ],
                        [ -2.55535, 51.49269 ],
                        [ -2.55185, 51.49225 ],
                        [ -2.54217, 51.49295 ],
                        [ -2.53734, 51.49702 ],
                        [ -2.53433, 51.49674 ]
                    ]
                ],
                "type": "Polygon"
            },
            "properties": {
                "name": "Bristol 014",
                "rg": "E02003025"
            },
            "type": "Feature"
        },
        {
            "geometry": {
                "coordinates": [
                    [
                        [
                            [ -2.61713, 51.47951 ],
                            [ -2.61552, 51.47151 ],
                            [ -2.62036, 51.46841 ],
                            [ -2.62023, 51.4661 ],
                            [ -2.62916, 51.46102 ],
                            [ -2.62984, 51.45761 ],
                            [ -2.63004, 51.46072 ],
                            [ -2.63224, 51.46646 ],
                            [ -2.63583, 51.46896 ],
                            [ -2.6439, 51.47077 ],
                            [ -2.64981, 51.47504 ],
                            [ -2.65078, 51.4798 ],
                            [ -2.64835, 51.48087 ],
                            [ -2.6433, 51.48582 ],
                            [ -2.64348, 51.48931 ],
                            [ -2.64197, 51.49173 ],
                            [ -2.63803, 51.49236 ],
                            [ -2.63206, 51.48746 ],
                            [ -2.62897, 51.48391 ],
                            [ -2.62001, 51.47943 ],
                            [ -2.61713, 51.47951 ]
                        ]
                    ],
                    [
                        [
                            [ -2.63116, 51.45761 ],
                            [ -2.63181, 51.45762 ],
                            [ -2.63178, 51.46154 ],
                            [ -2.63486, 51.46719 ],
                            [ -2.64676, 51.47085 ],
                            [ -2.65146, 51.47415 ],
                            [ -2.65262, 51.47921 ],
                            [ -2.65227, 51.47936 ],
                            [ -2.65137, 51.47497 ],
                            [ -2.64653, 51.47082 ],
                            [ -2.63582, 51.46788 ],
                            [ -2.63499, 51.46738 ],
                            [ -2.63369, 51.46634 ],
                            [ -2.63155, 51.46144 ],
                            [ -2.63116, 51.45761 ]
                        ]
                    ]
                ],
                "type": "MultiPolygon"
            },
            "properties": {
                "name": "Bristol 015",
                "rg": "E02003026"
            },
            "type": "Feature"
        },
        {
            "geometry": {
                "coordinates": [
                    [
                        [ -2.5765, 51.48055 ],
                        [ -2.57611, 51.47564 ],
                        [ -2.58048, 51.47581 ],
                        [ -2.58549, 51.47407 ],
                        [ -2.58719, 51.47489 ],
                        [ -2.59904, 51.47666 ],
                        [ -2.59938, 51.48098 ],
                        [ -2.60092, 51.48262 ],
                        [ -2.59152, 51.4873 ],
                        [ -2.58995, 51.48497 ],
                        [ -2.58322, 51.48419 ],
                        [ -2.58219, 51.48131 ],
                        [ -2.5765, 51.48055 ]
                    ]
                ],
                "type": "Polygon"
            },
            "properties": {
                "name": "Bristol 016",
                "rg": "E02003027"
            },
            "type": "Feature"
        },
        {
            "geometry": {
                "coordinates": [
                    [
                        [ -2.6128, 51.48381 ],
                        [ -2.61151, 51.48162 ],
                        [ -2.60676, 51.47922 ],
                        [ -2.60092, 51.48262 ],
                        [ -2.59938, 51.48098 ],
                        [ -2.59904, 51.47666 ],
                        [ -2.59764, 51.47403 ],
                        [ -2.6077, 51.47155 ],
                        [ -2.61036, 51.47249 ],
                        [ -2.61552, 51.47151 ],
                        [ -2.61713, 51.47951 ],
                        [ -2.61627, 51.48444 ],
                        [ -2.6128, 51.48381 ]
                    ]
                ],
                "type": "Polygon"
            },
            "properties": {
                "name": "Bristol 017",
                "rg": "E02003028"
            },
            "type": "Feature"
        },
        {
            "geometry": {
                "coordinates": [
                    [
                        [ -2.51523, 51.48145 ],
                        [ -2.51499, 51.48093 ],
                        [ -2.51118, 51.47418 ],
                        [ -2.51084, 51.47159 ],
                        [ -2.51293, 51.46915 ],
                        [ -2.5168, 51.46803 ],
                        [ -2.52298, 51.4721 ],
                        [ -2.52323, 51.47485 ],
                        [ -2.5258, 51.47834 ],
                        [ -2.52295, 51.47862 ],
                        [ -2.52154, 51.48169 ],
                        [ -2.51523, 51.48145 ]
                    ]
                ],
                "type": "Polygon"
            },
            "properties": {
                "name": "Bristol 018",
                "rg": "E02003029"
            },
            "type": "Feature"
        },
        {
            "geometry": {
                "coordinates": [
                    [
                        [ -2.53428, 51.47917 ],
                        [ -2.53604, 51.47675 ],
                        [ -2.54453, 51.47136 ],
                        [ -2.54136, 51.47031 ],
                        [ -2.54156, 51.46582 ],
                        [ -2.54768, 51.46428 ],
                        [ -2.55102, 51.46396 ],
                        [ -2.54976, 51.46884 ],
                        [ -2.55343, 51.47035 ],
                        [ -2.55409, 51.47353 ],
                        [ -2.56077, 51.47475 ],
                        [ -2.56035, 51.47864 ],
                        [ -2.55922, 51.48049 ],
                        [ -2.55566, 51.48133 ],
                        [ -2.54463, 51.48114 ],
                        [ -2.54751, 51.47856 ],
                        [ -2.54605, 51.47745 ],
                        [ -2.54084, 51.47735 ],
                        [ -2.53898, 51.48035 ],
                        [ -2.53428, 51.47917 ]
                    ]
                ],
                "type": "Polygon"
            },
            "properties": {
                "name": "Bristol 019",
                "rg": "E02003030"
            },
            "type": "Feature"
        },
        {
            "geometry": {
                "coordinates": [
                    [
                        [ -2.57611, 51.47564 ],
                        [ -2.57471, 51.47365 ],
                        [ -2.59121, 51.46704 ],
                        [ -2.59378, 51.47039 ],
                        [ -2.59788, 51.4691 ],
                        [ -2.60449, 51.47014 ],
                        [ -2.6077, 51.47155 ],
                        [ -2.59764, 51.47403 ],
                        [ -2.59904, 51.47666 ],
                        [ -2.58719, 51.47489 ],
                        [ -2.58549, 51.47407 ],
                        [ -2.58048, 51.47581 ],
                        [ -2.57611, 51.47564 ]
                    ]
                ],
                "type": "Polygon"
            },
            "properties": {
                "name": "Bristol 020",
                "rg": "E02003031"
            },
            "type": "Feature"
        },
        {
            "geometry": {
                "coordinates": [
                    [
                        [ -2.51293, 51.46915 ],
                        [ -2.51287, 51.46718 ],
                        [ -2.52118, 51.46664 ],
                        [ -2.52899, 51.46688 ],
                        [ -2.54156, 51.46582 ],
                        [ -2.54136, 51.47031 ],
                        [ -2.54453, 51.47136 ],
                        [ -2.53604, 51.47675 ],
                        [ -2.5258, 51.47834 ],
                        [ -2.52323, 51.47485 ],
                        [ -2.52298, 51.4721 ],
                        [ -2.5168, 51.46803 ],
                        [ -2.51293, 51.46915 ]
                    ]
                ],
                "type": "Polygon"
            },
            "properties": {
                "name": "Bristol 021",
                "rg": "E02003032"
            },
            "type": "Feature"
        },
        {
            "geometry": {
                "coordinates": [
                    [
                        [ -2.58757, 51.41106 ],
                        [ -2.58153, 51.40879 ],
                        [ -2.5844, 51.40041 ],
                        [ -2.59013, 51.39755 ],
                        [ -2.59258, 51.39728 ],
                        [ -2.5972, 51.39865 ],
                        [ -2.59705, 51.40016 ],
                        [ -2.60487, 51.40044 ],
                        [ -2.6104, 51.40127 ],
                        [ -2.60964, 51.40378 ],
                        [ -2.60553, 51.40514 ],
                        [ -2.60298, 51.40766 ],
                        [ -2.60256, 51.40986 ],
                        [ -2.59468, 51.41066 ],
                        [ -2.59433, 51.41384 ],
                        [ -2.59361, 51.41416 ],
                        [ -2.58757, 51.41106 ]
                    ]
                ],
                "type": "Polygon"
            },
            "properties": {
                "name": "Bristol 053",
                "rg": "E02003064"
            },
            "type": "Feature"
        },
        {
            "geometry": {
                "coordinates": [
                    [
                        [ -2.56406, 51.44494 ],
                        [ -2.57165, 51.44318 ],
                        [ -2.5767, 51.44416 ],
                        [ -2.57714, 51.44766 ],
                        [ -2.57986, 51.44832 ],
                        [ -2.58175, 51.44789 ],
                        [ -2.58558, 51.44578 ],
                        [ -2.59109, 51.44581 ],
                        [ -2.59037, 51.4485 ],
                        [ -2.59204, 51.4495 ],
                        [ -2.59199, 51.45262 ],
                        [ -2.58928, 51.45484 ],
                        [ -2.58414, 51.45277 ],
                        [ -2.58459, 51.45706 ],
                        [ -2.58616, 51.45905 ],
                        [ -2.57992, 51.4619 ],
                        [ -2.57692, 51.46097 ],
                        [ -2.57517, 51.45606 ],
                        [ -2.57184, 51.45334 ],
                        [ -2.56857, 51.44508 ],
                        [ -2.56406, 51.44494 ]
                    ]
                ],
                "type": "Polygon"
            },
            "properties": {
                "name": "Bristol 054",
                "rg": "E02006887"
            },
            "type": "Feature"
        },
        {
            "geometry": {
                "coordinates": [
                    [
                        [ -2.55634, 51.46336 ],
                        [ -2.55966, 51.46267 ],
                        [ -2.55978, 51.4584 ],
                        [ -2.56305, 51.45766 ],
                        [ -2.57242, 51.45945 ],
                        [ -2.57126, 51.46296 ],
                        [ -2.57168, 51.46568 ],
                        [ -2.57002, 51.46804 ],
                        [ -2.56785, 51.46891 ],
                        [ -2.56384, 51.46349 ],
                        [ -2.55634, 51.46336 ]
                    ]
                ],
                "type": "Polygon"
            },
            "properties": {
                "name": "Bristol 055",
                "rg": "E02006888"
            },
            "type": "Feature"
        },
        {
            "geometry": {
                "coordinates": [
                    [
                        [ -2.56305, 51.45766 ],
                        [ -2.56055, 51.45495 ],
                        [ -2.55944, 51.45188 ],
                        [ -2.55205, 51.452 ],
                        [ -2.55395, 51.45106 ],
                        [ -2.55918, 51.449 ],
                        [ -2.55823, 51.44704 ],
                        [ -2.56406, 51.44494 ],
                        [ -2.56857, 51.44508 ],
                        [ -2.57184, 51.45334 ],
                        [ -2.57517, 51.45606 ],
                        [ -2.57692, 51.46097 ],
                        [ -2.57992, 51.4619 ],
                        [ -2.5738, 51.46683 ],
                        [ -2.57002, 51.46804 ],
                        [ -2.57168, 51.46568 ],
                        [ -2.57126, 51.46296 ],
                        [ -2.57242, 51.45945 ],
                        [ -2.56305, 51.45766 ]
                    ]
                ],
                "type": "Polygon"
            },
            "properties": {
                "name": "Bristol 056",
                "rg": "E02006889"
            },
            "type": "Feature"
        },
        {
            "geometry": {
                "coordinates": [
                    [
                        [ -2.55102, 51.46396 ],
                        [ -2.55634, 51.46336 ],
                        [ -2.56384, 51.46349 ],
                        [ -2.56785, 51.46891 ],
                        [ -2.56194, 51.47296 ],
                        [ -2.56077, 51.47475 ],
                        [ -2.55409, 51.47353 ],
                        [ -2.55343, 51.47035 ],
                        [ -2.54976, 51.46884 ],
                        [ -2.55102, 51.46396 ]
                    ]
                ],
                "type": "Polygon"
            },
            "properties": {
                "name": "Bristol 057",
                "rg": "E02006890"
            },
            "type": "Feature"
        }
    ],
    "type": "FeatureCollection"
}
